{
  "editor:insert-codeblock": [
    {
      "modifiers": [
        "Mod"
      ],
      "key": "`"
    }
  ],
  "workspace:split-vertical": [
    {
      "modifiers": [
        "Alt",
        "Mod"
      ],
      "key": "\\"
    }
  ],
  "editor:toggle-highlight": [
    {
      "modifiers": [
        "Mod",
        "Shift"
      ],
      "key": "="
    }
  ],
  "insert-template": [
    {
      "modifiers": [
        "Mod"
      ],
      "key": "Q"
    }
  ],
  "global-search:open": [
    {
      "modifiers": [
        "Mod",
        "Shift"
      ],
      "key": "F"
    }
  ],
  "editor:toggle-blockquote": [
    {
      "modifiers": [
        "Mod",
        "Shift"
      ],
      "key": "."
    }
  ],
  "editor:delete-paragraph": [],
  "emacs-text-editor:move-end-of-line": [
    {
      "modifiers": [
        "Mod"
      ],
      "key": "E"
    }
  ],
  "command-palette:open": [
    {
      "modifiers": [
        "Mod",
        "Shift"
      ],
      "key": "P"
    }
  ],
  "emacs-text-editor:backward-char": [
    {
      "modifiers": [
        "Mod"
      ],
      "key": "B"
    }
  ],
  "emacs-text-editor:forward-word": [
    {
      "modifiers": [
        "Alt"
      ],
      "key": "F"
    }
  ],
  "editor:toggle-bold": [],
  "emacs-text-editor:forward-char": [
    {
      "modifiers": [
        "Mod"
      ],
      "key": "F"
    }
  ],
  "editor:open-search": [],
  "emacs-text-editor:backward-word": [
    {
      "modifiers": [
        "Alt"
      ],
      "key": "B"
    }
  ],
  "file-explorer:new-file": [],
  "emacs-text-editor:next-line": [
    {
      "modifiers": [
        "Mod"
      ],
      "key": "N"
    }
  ],
  "emacs-text-editor:previous-line": [
    {
      "modifiers": [
        "Mod"
      ],
      "key": "P"
    }
  ],
  "app:toggle-right-sidebar": [
    {
      "modifiers": [
        "Alt"
      ],
      "key": "ArrowRight"
    }
  ],
  "app:toggle-left-sidebar": [
    {
      "modifiers": [
        "Alt"
      ],
      "key": "ArrowLeft"
    }
  ],
  "emacs-text-editor:forward-paragraph": [
    {
      "modifiers": [
        "Mod"
      ],
      "key": "D"
    }
  ],
  "emacs-text-editor:backward-paragraph": [
    {
      "modifiers": [
        "Mod"
      ],
      "key": "U"
    }
  ],
  "workspace:close": [],
  "switcher:open": [
    {
      "modifiers": [
        "Mod",
        "Shift"
      ],
      "key": "O"
    }
  ],
  "markdown:toggle-preview": [
    {
      "modifiers": [
        "Alt",
        "Mod"
      ],
      "key": "E"
    }
  ],
  "file-explorer:move-file": [
    {
      "modifiers": [
        "Mod",
        "Shift"
      ],
      "key": "M"
    }
  ]
}